api/__init__.py
galaxylearning/__init__.py
galaxylearning/core/__init__.py
galaxylearning/core/aggregator.py
galaxylearning/core/communicate_client.py
galaxylearning/core/communicate_server.py
galaxylearning/core/job_manager.py
galaxylearning/core/server.py
galaxylearning/core/strategy.py
galaxylearning/core/trainer.py
galaxylearning/core/trainer_controller.py
galaxylearning/entity/__init__.py
galaxylearning/entity/job.py
galaxylearning/entity/runtime_config.py
galaxylearning/exceptions/__init__.py
galaxylearning/exceptions/fl_expection.py
galaxylearning/lib/__init__.py
galaxylearning/utils/__init__.py
galaxylearning/utils/utils.py
galaxylearning-0.1.1.dist-info/LICENSE
galaxylearning-0.1.1.dist-info/METADATA
galaxylearning-0.1.1.dist-info/WHEEL
galaxylearning-0.1.1.dist-info/top_level.txt
galaxylearning-0.1.1.dist-info/zip-safe
galaxylearning-0.1.1.dist-info/RECORD
