Metadata-Version: 2.1
Name: galaxylearning
Version: 0.1.1
Summary: A Federated Learning Package Based on pytorch
Home-page: https://github.com/ZJU-DistributedAI/galaxylearningaxyLearning
Author: galaxylearningaxy Learning Author
Author-email: yifan_hu@zju.edu.cn
License: Apache-2.0
Platform: UNKNOWN
Classifier: Intended Audience :: Developers
Classifier: Intended Audience :: Education
Classifier: Intended Audience :: Science/Research
Classifier: License :: OSI Approved :: Apache Software License
Classifier: Programming Language :: Python :: 3
Classifier: Programming Language :: Python :: 3.4
Classifier: Programming Language :: Python :: 3.5
Classifier: Programming Language :: Python :: 3.6
Classifier: Topic :: Scientific/Engineering
Classifier: Topic :: Scientific/Engineering :: Mathematics
Classifier: Topic :: Scientific/Engineering :: Artificial Intelligence
Classifier: Topic :: Software Development
Classifier: Topic :: Software Development :: Libraries
Classifier: Topic :: Software Development :: Libraries :: Python Modules
